Metadata-Version: 2.1
Name: PipTestMining
Version: 0.0.5
Summary: PipTest
Home-page: https://github.com/Dragonwyj/tmp
Author: wangyijun
Author-email: dragonwyj@163.com
License: UNKNOWN
Platform: UNKNOWN
Classifier: Programming Language :: Python :: 3
Classifier: License :: OSI Approved :: MIT License
Classifier: Operating System :: OS Independent
